setup.py
dalab2test/__init__.py
dalab2test/numpy_implementation.py
dalab2test.egg-info/PKG-INFO
dalab2test.egg-info/SOURCES.txt
dalab2test.egg-info/dependency_links.txt
dalab2test.egg-info/not-zip-safe
dalab2test.egg-info/top_level.txt