Metadata-Version: 1.0
Name: dalab2test
Version: 0.2
Summary: Test numpy implementation for DA LAB2
Home-page: UNKNOWN
Author: Dmitriy Kolchin
Author-email: 284594@niuitmo.ru
License: UNKNOWN
Platform: UNKNOWN
